{
    "title": "SSbreakingHeadlines",
    "link": "http://example.com/interleaved_feed.json",
    "description": "This is a randomly ordered feed of the most recent entries from SSbreakingHeadlines, skipping any feeds with errors.",
    "lastBuildDate": "2026-04-23T16:22:30.980169",
    "items": [
        {
            "title": "Shooting at Louisiana mall stemmed from argument between two groups, police say",
            "link": "https://www.cbsnews.com/video/shooting-at-louisiana-mall-stemmed-from-argument-between-two-groups-police-say/",
            "description": "Police in Baton Rouge say a shooting broke out Thursday at the Mall of Louisiana after an argument between two groups of people. Multiple people were ...",
            "pubDate": "2026-04-23T21:01:33",
            "image_url": "https://spyd3rwebs.github.io/rss/genNewsImagesTwo/Picture9.png"
        },
        {
            "title": "WATCH:  What does reclassification mean for marijuana users?",
            "link": "https://abcnews.com/video/132321999/",
            "description": "A new order moves marijuana from Schedule I to Schedule III, putting state-licensed medical marijuana in the same category as some pain medications, k...",
            "pubDate": "2026-04-23T19:09:28",
            "image_url": "https://spyd3rwebs.github.io/rss/genNewsImagesTwo/Picture9.png"
        },
        {
            "title": "Here's how much interest a $15,000 money market account can earn now",
            "link": "https://www.cbsnews.com/news/how-much-interest-15000-money-market-account-earn-april-2026/",
            "description": "interest earnings on a $15,000 money market account can still be significant. Here's what savers need to know now.",
            "pubDate": "2026-04-23T20:42:25",
            "image_url": "https://spyd3rwebs.github.io/rss/genNewsImagesTwo/Picture2.png"
        },
        {
            "title": "Meta to cut 8,000 jobs as it charges into AI",
            "link": "https://www.cbsnews.com/news/meta-layoffs-8000-ai-job-cuts/",
            "description": "Meta plans to lay off roughly 10% of its workforce as the technology giant steps up its spending on artificial intelligence.",
            "pubDate": "2026-04-23T20:49:22",
            "image_url": "https://spyd3rwebs.github.io/rss/genNewsImagesTwo/Picture4.png"
        },
        {
            "title": "Debris from Hurricane Helene is helping fuel Georgia’s wildfires",
            "link": "https://apnews.com/article/georgia-florida-wildfires-drought-32380497738fbf66283e32c597b931fc",
            "description": "",
            "pubDate": "2026-04-23T11:38:14",
            "image_url": "https://spyd3rwebs.github.io/rss/genNewsImagesTwo/Picture9.png"
        },
        {
            "title": "WATCH:  1st look at 'The Cult of NatureBoy'",
            "link": "https://abcnews.com/video/132309102/",
            "description": "\"GMA\" shares a preview at the new Hulu docuseries following social media figure NatureBoy and his followers in search of utopia.",
            "pubDate": "2026-04-23T16:53:42",
            "image_url": "https://spyd3rwebs.github.io/rss/genNewsImagesTwo/Picture3.png"
        },
        {
            "title": "LaGuardia firefighter heard ‘stop, stop, stop’ before deadly crash but didn’t know who it was for",
            "link": "https://apnews.com/article/laguardia-air-canada-ntsb-crash-fire-truck-8f59cffd6f8230ec0c0c0c4d6efbab25",
            "description": "",
            "pubDate": "2026-04-23T15:42:40",
            "image_url": "https://spyd3rwebs.github.io/rss/genNewsImagesTwo/Picture1.png"
        },
        {
            "title": "WATCH:  ‘GMA’ anchors get quizzed by kids",
            "link": "https://abcnews.com/video/132308524/",
            "description": "On Bring a Kid to Work Day, the children of “GMA” staffers put questions to the morning show’s anchors.",
            "pubDate": "2026-04-23T16:53:20",
            "image_url": "https://spyd3rwebs.github.io/rss/genNewsImagesTwo/Picture5.png"
        },
        {
            "title": "Iran live updates: Trump orders Navy to 'shoot,' 'kill' boats putting mines in strait",
            "link": "https://abcnews.com/International/live-updates/iran-live-updates-marines-uss-tripoli-seized-iranian/?id=132196152",
            "description": "President Donald Trump announced \"major combat operations\" against Iran on Feb. 28, with massive joint U.S.-Israeli strikes.",
            "pubDate": "2026-04-23T20:07:17",
            "image_url": "https://spyd3rwebs.github.io/rss/genNewsImagesTwo/Picture7.png"
        },
        {
            "title": "At least 10 people injured in shooting at Mall of Louisiana, police say",
            "link": "https://www.cbsnews.com/live-updates/shooting-mall-of-louisiana/",
            "description": "Police said the shooting appeared to have happened after two groups of people got into an argument in the mall's food court.",
            "pubDate": "2026-04-23T21:16:44",
            "image_url": "https://spyd3rwebs.github.io/rss/genNewsImagesTwo/Picture9.png"
        },
        {
            "title": "10 hurt in shooting at mall in Louisiana, suspect at large: Officials",
            "link": "https://abcnews.com/US/multiple-victims-reported-shooting-mall-louisiana-officials/story?id=132325015",
            "description": "Ten people have been hurt in a shooting at the Mall of Louisiana in Baton Rouge, officials said.",
            "pubDate": "2026-04-23T21:18:24",
            "image_url": "https://spyd3rwebs.github.io/rss/genNewsImagesTwo/Picture5.png"
        },
        {
            "title": "Michael Tilson Thomas on his love of music | 60 Minutes Archive",
            "link": "https://www.cbsnews.com/video/michael-tilson-thomas-on-his-love-of-music-60-minutes-archive/",
            "description": "In 2000, Morley Safer spoke with conductor Michael Tilson Thomas about his love of music, music's message and more. Thomas, who died Wednesday at age ...",
            "pubDate": "2026-04-23T21:16:56",
            "image_url": "https://spyd3rwebs.github.io/rss/genNewsImagesTwo/Picture9.png"
        },
        {
            "title": "Trump reclassifies state-licensed medical marijuana as a less-dangerous drug in a historic shift",
            "link": "https://apnews.com/article/medical-marijuana-rescheduling-justice-department-trump-cannabis-1d6722d3aae122b1a91f8e4b6c690268",
            "description": "A cannabis industry group calls President Donald Trump’s reclassification of state-licensed medical marijuana as a less-dangerous drug “the most signi...",
            "pubDate": "2026-04-23T09:16:37",
            "image_url": "https://spyd3rwebs.github.io/rss/genNewsImagesTwo/Picture5.png"
        }
    ]
}