{
    "title": "Individual feed for https://juliaberolzheimer.com/feed/",
    "link": "https://juliaberolzheimer.com/feed/",
    "description": "Individual feed output.",
    "lastBuildDate": "2026-02-24T16:09:57.913679",
    "items": [
        {
            "title": "Butter Yellow Head to Toe",
            "link": "https://juliaberolzheimer.com/2026/02/trend-butter-yellow/",
            "description": "Lisa Yang Tank & Sweater, Leset Pants, Proenza Schouler Heels (more sizes here, similar here), Chanel Bag, Arielle Ratner Necklace Butter yellow has c...",
            "pubDate": "2026-02-24T05:00:40",
            "image_url": "https://juliaberolzheimer.com/wp-content/uploads/2026/02/20260213-jb-lisa-yang-tank-sweater-leset-pants-1000972-1024x1536.jpg"
        },
        {
            "title": "Amazon Sundays: Effortless Lux Beauty",
            "link": "https://juliaberolzheimer.com/2026/02/amazon-sundays-effortless-lux-beauty/",
            "description": "This week’s lineup reads like a tightly edited apothecary — micellar waters with cult followings, super hydrating creams known for… The post Amazon Su...",
            "pubDate": "2026-02-22T05:00:39",
            "image_url": "https://lead-mark.github.io/snippets/genNewsImagesTwo/Picture3.png"
        },
        {
            "title": "The Occasion Dress Edit: Sunset & Reservations",
            "link": "https://juliaberolzheimer.com/2026/02/the-occasion-dress-edit-sunset-reservations/",
            "description": "Alemais Dress, Le Sundial Belt, Valentino Bag, Irene Neuwirth Earrings, Arielle Ratner Necklace The best part about vacation is having an excuse to dr...",
            "pubDate": "2026-02-20T05:00:47",
            "image_url": "https://juliaberolzheimer.com/wp-content/uploads/2026/02/20260122-jb-alemais-dress-valentino-bag-1007245-1024x1536.jpg"
        },
        {
            "title": "Maximalist Moment- Pieces With Details",
            "link": "https://juliaberolzheimer.com/2026/02/maximalist-moment-pieces-with-details/",
            "description": "LaPointe Top, Dries Van Noten Pants, Prada Bag, Irene Neuwirth Earrings For seasons, restraint may have shaped the conversation, but spring shifts the...",
            "pubDate": "2026-02-19T05:00:37",
            "image_url": "https://juliaberolzheimer.com/wp-content/uploads/2026/02/20260123-jb-LaPointe-Top-Dries-Van-Noten-Pants-1008131-1024x1536.jpg"
        },
        {
            "title": "Sheer Pastels as New Neutrals",
            "link": "https://juliaberolzheimer.com/2026/02/sheer-pastels-as-new-neutrals/",
            "description": "Toteme Shirt (old, similar here and here), Eterne Tank, Pucci Skirt, Polo Ralph Lauren Hat, Hermes Tote, Dior Sunglasses When color is rendered transp...",
            "pubDate": "2026-02-18T05:00:32",
            "image_url": "https://juliaberolzheimer.com/wp-content/uploads/2026/02/20260122-jb-toteme-shirt-eterne-tank-pucci-skirt-1007118-1024x1536.jpg"
        }
    ]
}