{
    "title": "Individual feed for https://www.nothankstocake.com/feed/",
    "link": "https://www.nothankstocake.com/feed/",
    "description": "Individual feed output.",
    "lastBuildDate": "2026-04-23T09:38:50.937246",
    "items": [
        {
            "title": "error",
            "link": "error",
            "description": "error",
            "pubDate": "2026-04-23T09:38:50.937143",
            "image_url": "error"
        },
        {
            "title": "error",
            "link": "error",
            "description": "error",
            "pubDate": "2026-04-23T09:38:50.937146",
            "image_url": "error"
        },
        {
            "title": "error",
            "link": "error",
            "description": "error",
            "pubDate": "2026-04-23T09:38:50.937147",
            "image_url": "error"
        }
    ]
}