{
    "title": "Individual feed for https://feeds.content.dowjones.io/public/rss/mw_topstories",
    "link": "https://feeds.content.dowjones.io/public/rss/mw_topstories",
    "description": "Individual feed output.",
    "lastBuildDate": "2026-03-10T07:59:03.935994",
    "items": [
        {
            "title": "Bill Ackman tries again with plan for IPO of Pershing Square and a new fund",
            "link": "https://www.marketwatch.com/story/bill-ackman-tries-again-with-plan-for-ipo-of-pershing-square-and-a-new-fund-084ae953?mod=mw_rss_topstories",
            "description": "Hedge fund manager Bill Ackman is again trying to take his fund management company public alongside the launch of a new fund.",
            "pubDate": "2026-03-10T12:47:00",
            "image_url": "https://images.mktw.net/im-72768616"
        },
        {
            "title": "Scientists behind COVID-19 vaccine will depart BioNTech",
            "link": "https://www.marketwatch.com/story/scientists-behind-covid-19-vaccine-will-depart-biontech-ef157c79?mod=mw_rss_topstories",
            "description": "The company’s co-founders said they are leaving to start a new mRNA-based company.",
            "pubDate": "2026-03-10T12:40:00",
            "image_url": "https://images.mktw.net/im-26579977"
        },
        {
            "title": "Return to the 2022 stock-market playbook as Iran conflict drags on, say these strategists",
            "link": "https://www.marketwatch.com/story/return-to-the-2022-stock-market-playbook-as-iran-conflict-drags-on-say-these-strategists-7bb7e01b?mod=mw_rss_topstories",
            "description": "Barclays says the chasm between winning and losing stocks in 2022 when Russia invaded Ukraine was huge. Here are their style picks.",
            "pubDate": "2026-03-10T12:28:00",
            "image_url": "https://images.mktw.net/im-08226732"
        },
        {
            "title": "Saudi Aramco promises full production can be restored within days if Strait of Hormuz is reopened",
            "link": "https://www.marketwatch.com/story/saudi-aramco-promises-full-production-can-be-restored-within-days-if-strait-of-hormuz-is-reopened-5741bad3?mod=mw_rss_topstories",
            "description": "Aramco’s CEO warns of “catastrophic consequences” for the oil market if the effective closure of the Straits Of Hormuz were to remain for an extended ...",
            "pubDate": "2026-03-10T12:16:00",
            "image_url": "https://images.mktw.net/im-89332095"
        },
        {
            "title": "Social Security is already the best antipoverty program we have — don’t make this radical change",
            "link": "https://www.marketwatch.com/story/social-security-is-already-the-best-antipoverty-program-we-have-dont-make-this-radical-change-929619b8?mod=mw_rss_topstories",
            "description": "Changing Social Security to a flat benefit for all would put both workers and the poor at risk.",
            "pubDate": "2026-03-10T12:00:00",
            "image_url": "https://images.mktw.net/im-11604130"
        }
    ]
}